setup.py
ha_oder/__init__.py
ha_oder/ha_oder.py
ha_oder.egg-info/PKG-INFO
ha_oder.egg-info/SOURCES.txt
ha_oder.egg-info/dependency_links.txt
ha_oder.egg-info/top_level.txt