Metadata-Version: 2.1
Name: ha_oder
Version: 9.0.5
Summary: telegram 
Author: Programmer king 
Classifier: Programming Language :: Python :: 3
Classifier: Operating System :: OS Independent
Classifier: License :: OSI Approved :: MIT License
